{
    "analysis_timestamp": "2025-03-26 14:15:38",
    "input_file": "dashboard/data/data.csv",
    "output_directory": "dashboard/data",
    "data_rows": 1000,
    "data_columns": 35,
    "aggregated_datasets": [
        "process_types",
        "process_steps",
        "process_type_step",
        "safety_parameters",
        "optimal_conditions"
    ],
    "derived_metrics": [
        "Energy_Efficiency",
        "Material_Productivity",
        "Cost_Efficiency",
        "Safety_Risk",
        "Has_Incident",
        "Environmental_Impact",
        "Processing_Speed",
        "Worker_Productivity",
        "Process_KPI_Score",
        "Duration_Category",
        "Temperature_Category",
        "Pressure_Category"
    ],
    "execution_time_seconds": 1.57
}